security_dependency_pinning/__init__.py
security_dependency_pinning/__init__conf__.py
security_dependency_pinning/__main__.py
security_dependency_pinning/behaviors.py
security_dependency_pinning/cli.py
security_dependency_pinning/py.typed
security_dependency_pinning-2.0.1.dist-info/METADATA
security_dependency_pinning-2.0.1.dist-info/WHEEL
security_dependency_pinning-2.0.1.dist-info/entry_points.txt
security_dependency_pinning-2.0.1.dist-info/licenses/LICENSE
security_dependency_pinning-2.0.1.dist-info/RECORD
