Metadata-Version: 2.4
Name: security_dependency_pinning
Version: 2.0.1
Summary: A repository dedicated to maintaining a secure, stable environment by pinning critical library versions to protect against vulnerabilities and ensure compatibility.
Project-URL: Homepage, https://github.com/bitranox/security_dependency_pinning
Project-URL: Repository, https://github.com/bitranox/security_dependency_pinning.git
Project-URL: Issues, https://github.com/bitranox/security_dependency_pinning/issues
Author-email: bitranox <bitranox@gmail.com>
License: MIT
License-File: LICENSE
Keywords: pinning,security,secutity-pinning
Classifier: Environment :: Console
Classifier: License :: OSI Approved :: MIT License
Classifier: Operating System :: OS Independent
Classifier: Programming Language :: Python :: 3
Classifier: Programming Language :: Python :: 3 :: Only
Classifier: Typing :: Typed
Requires-Python: >=3.13
Requires-Dist: certifi>=2024.2.2
Requires-Dist: lib-cli-exit-tools>=2.1.0
Requires-Dist: pygments>=2.7.4
Requires-Dist: requests[security]>=2.32.4
Requires-Dist: rich-click>=1.9.4
Requires-Dist: urllib3>=2.5.0
Requires-Dist: uwsgi>=2.0.21; sys_platform != 'win32'
Requires-Dist: zipp>=3.19.1
Provides-Extra: dev
Requires-Dist: bandit>=1.8.6; extra == 'dev'
Requires-Dist: build>=1.3.0; extra == 'dev'
Requires-Dist: codecov-cli>=11.2.3; extra == 'dev'
Requires-Dist: import-linter>=2.5.2; extra == 'dev'
Requires-Dist: pip-audit>=2.9.0; extra == 'dev'
Requires-Dist: pyright>=1.1.406; extra == 'dev'
Requires-Dist: pytest-cov>=7.0.0; extra == 'dev'
Requires-Dist: pytest>=8.4.2; extra == 'dev'
Requires-Dist: ruff>=0.14.3; extra == 'dev'
Requires-Dist: textual>=6.3.0; extra == 'dev'
Requires-Dist: twine>=6.2.0; extra == 'dev'
